<?xml version='1.0' encoding='utf-8'?>
<annotation>
	<folder>大青叶蝉</folder>
	<filename>104044.jpg</filename>
	<path>104044.jpg</path>
	<source>
		<database>Unknown</database>
	</source>
	<size>
		<width>501</width>
		<height>336</height>
		<depth>3</depth>
	</size>
	<segmented>0</segmented>
	<object>
		<name>大青叶蝉</name>
		<pose>Unspecified</pose>
		<truncated>0</truncated>
		<difficult>0</difficult>
		<bndbox>
			<xmin>89</xmin>
			<ymin>166</ymin>
			<xmax>277</xmax>
			<ymax>296</ymax>
		</bndbox>
	</object>
</annotation>