<?xml version='1.0' encoding='utf-8'?>
<annotation>
	<folder>云斑白条天牛</folder>
	<filename>119053.jpg</filename>
	<path>119053.jpg</path>
	<source>
		<database>Unknown</database>
	</source>
	<size>
		<width>690</width>
		<height>516</height>
		<depth>3</depth>
	</size>
	<segmented>0</segmented>
	<object>
		<name>云斑白条天牛</name>
		<pose>Unspecified</pose>
		<truncated>0</truncated>
		<difficult>0</difficult>
		<bndbox>
			<xmin>79</xmin>
			<ymin>371</ymin>
			<xmax>165</xmax>
			<ymax>510</ymax>
		</bndbox>
	</object>
</annotation>